<?xml version="1.0" encoding="UTF-8" standalone="no"?><definitions targetNamespace="http://www.activiti.org/test" xmlns="http://www.omg.org/spec/BPMN/20100524/MODEL"><process id="xor_10" isExecutable="true" name="xor_10"><startEvent id="startEvent" name="startEvent"/><endEvent id="endEvent" name="endEvent"/><exclusiveGateway default="xor1_st1" id="xor1" name="xor1"/><serviceTask xmlns:ns0="http://activiti.org/bpmn" ns0:class="org.wso2.carbon.bps.perf.services.Service1" id="st1" name="st1"/><sequenceFlow id="xor1_st1" sourceRef="xor1" targetRef="st1"/><sequenceFlow id="st1_endEvent" sourceRef="st1" targetRef="endEvent"/><sequenceFlow id="startEvent_xor1" sourceRef="startEvent" targetRef="xor1"/><exclusiveGateway default="xor2_st2" id="xor2" name="xor2"/><serviceTask xmlns:ns0="http://activiti.org/bpmn" ns0:class="org.wso2.carbon.bps.perf.services.Service1" id="st2" name="st2"/><sequenceFlow id="xor2_st2" sourceRef="xor2" targetRef="st2"/><sequenceFlow id="st2_endEvent" sourceRef="st2" targetRef="endEvent"/><sequenceFlow id="xor1_xor2" sourceRef="xor1" targetRef="xor2"><conditionExpression xmlns:ns0="http://www.w3.org/2001/XMLSchema-instance" ns0:type="tFormalExpression"><![CDATA[${v1 >= 2}]]></conditionExpression></sequenceFlow><exclusiveGateway default="xor3_st3" id="xor3" name="xor3"/><serviceTask xmlns:ns0="http://activiti.org/bpmn" ns0:class="org.wso2.carbon.bps.perf.services.Service1" id="st3" name="st3"/><sequenceFlow id="xor3_st3" sourceRef="xor3" targetRef="st3"/><sequenceFlow id="st3_endEvent" sourceRef="st3" targetRef="endEvent"/><sequenceFlow id="xor2_xor3" sourceRef="xor2" targetRef="xor3"><conditionExpression xmlns:ns0="http://www.w3.org/2001/XMLSchema-instance" ns0:type="tFormalExpression"><![CDATA[${v1 >= 3}]]></conditionExpression></sequenceFlow><exclusiveGateway default="xor4_st4" id="xor4" name="xor4"/><serviceTask xmlns:ns0="http://activiti.org/bpmn" ns0:class="org.wso2.carbon.bps.perf.services.Service1" id="st4" name="st4"/><sequenceFlow id="xor4_st4" sourceRef="xor4" targetRef="st4"/><sequenceFlow id="st4_endEvent" sourceRef="st4" targetRef="endEvent"/><sequenceFlow id="xor3_xor4" sourceRef="xor3" targetRef="xor4"><conditionExpression xmlns:ns0="http://www.w3.org/2001/XMLSchema-instance" ns0:type="tFormalExpression"><![CDATA[${v1 >= 4}]]></conditionExpression></sequenceFlow><exclusiveGateway default="xor5_st5" id="xor5" name="xor5"/><serviceTask xmlns:ns0="http://activiti.org/bpmn" ns0:class="org.wso2.carbon.bps.perf.services.Service1" id="st5" name="st5"/><sequenceFlow id="xor5_st5" sourceRef="xor5" targetRef="st5"/><sequenceFlow id="st5_endEvent" sourceRef="st5" targetRef="endEvent"/><sequenceFlow id="xor4_xor5" sourceRef="xor4" targetRef="xor5"><conditionExpression xmlns:ns0="http://www.w3.org/2001/XMLSchema-instance" ns0:type="tFormalExpression"><![CDATA[${v1 >= 5}]]></conditionExpression></sequenceFlow><exclusiveGateway default="xor6_st6" id="xor6" name="xor6"/><serviceTask xmlns:ns0="http://activiti.org/bpmn" ns0:class="org.wso2.carbon.bps.perf.services.Service1" id="st6" name="st6"/><sequenceFlow id="xor6_st6" sourceRef="xor6" targetRef="st6"/><sequenceFlow id="st6_endEvent" sourceRef="st6" targetRef="endEvent"/><sequenceFlow id="xor5_xor6" sourceRef="xor5" targetRef="xor6"><conditionExpression xmlns:ns0="http://www.w3.org/2001/XMLSchema-instance" ns0:type="tFormalExpression"><![CDATA[${v1 >= 6}]]></conditionExpression></sequenceFlow><exclusiveGateway default="xor7_st7" id="xor7" name="xor7"/><serviceTask xmlns:ns0="http://activiti.org/bpmn" ns0:class="org.wso2.carbon.bps.perf.services.Service1" id="st7" name="st7"/><sequenceFlow id="xor7_st7" sourceRef="xor7" targetRef="st7"/><sequenceFlow id="st7_endEvent" sourceRef="st7" targetRef="endEvent"/><sequenceFlow id="xor6_xor7" sourceRef="xor6" targetRef="xor7"><conditionExpression xmlns:ns0="http://www.w3.org/2001/XMLSchema-instance" ns0:type="tFormalExpression"><![CDATA[${v1 >= 7}]]></conditionExpression></sequenceFlow><exclusiveGateway default="xor8_st8" id="xor8" name="xor8"/><serviceTask xmlns:ns0="http://activiti.org/bpmn" ns0:class="org.wso2.carbon.bps.perf.services.Service1" id="st8" name="st8"/><sequenceFlow id="xor8_st8" sourceRef="xor8" targetRef="st8"/><sequenceFlow id="st8_endEvent" sourceRef="st8" targetRef="endEvent"/><sequenceFlow id="xor7_xor8" sourceRef="xor7" targetRef="xor8"><conditionExpression xmlns:ns0="http://www.w3.org/2001/XMLSchema-instance" ns0:type="tFormalExpression"><![CDATA[${v1 >= 8}]]></conditionExpression></sequenceFlow><exclusiveGateway default="xor9_st9" id="xor9" name="xor9"/><serviceTask xmlns:ns0="http://activiti.org/bpmn" ns0:class="org.wso2.carbon.bps.perf.services.Service1" id="st9" name="st9"/><sequenceFlow id="xor9_st9" sourceRef="xor9" targetRef="st9"/><sequenceFlow id="st9_endEvent" sourceRef="st9" targetRef="endEvent"/><sequenceFlow id="xor8_xor9" sourceRef="xor8" targetRef="xor9"><conditionExpression xmlns:ns0="http://www.w3.org/2001/XMLSchema-instance" ns0:type="tFormalExpression"><![CDATA[${v1 >= 9}]]></conditionExpression></sequenceFlow><exclusiveGateway default="xor10_st10" id="xor10" name="xor10"/><serviceTask xmlns:ns0="http://activiti.org/bpmn" ns0:class="org.wso2.carbon.bps.perf.services.Service1" id="st10" name="st10"/><sequenceFlow id="xor10_st10" sourceRef="xor10" targetRef="st10"/><sequenceFlow id="st10_endEvent" sourceRef="st10" targetRef="endEvent"/><sequenceFlow id="xor9_xor10" sourceRef="xor9" targetRef="xor10"><conditionExpression xmlns:ns0="http://www.w3.org/2001/XMLSchema-instance" ns0:type="tFormalExpression"><![CDATA[${v1 >= 10}]]></conditionExpression></sequenceFlow><serviceTask xmlns:ns0="http://activiti.org/bpmn" ns0:class="org.wso2.carbon.bps.perf.services.Service1" id="st_condition" name="st_condition"/><sequenceFlow id="xor10_st_condition" sourceRef="xor10" targetRef="st_condition"><conditionExpression xmlns:ns0="http://www.w3.org/2001/XMLSchema-instance" ns0:type="tFormalExpression"><![CDATA[${v1 > 10000}]]></conditionExpression></sequenceFlow><sequenceFlow id="st_condition_endEvent" sourceRef="st_condition" targetRef="endEvent"/></process></definitions>